{
  "canonical_subject_key": "arch.records.group",
  "has_conflict": false,
  "latest_active_record_id": "mem:observed_fact:arch.index.types.confirme.active.by.domain.records.group:4beb74ee",
  "record_count": 1,
  "records": [
    {
      "authority": "observed",
      "canonical_subject_key": "arch.records.group",
      "id": "mem:observed_fact:arch.index.types.confirme.active.by.domain.records.group:4beb74ee",
      "index_status": "active",
      "kind": "observed_fact",
      "provenance": {
        "locator": "Index types \u2014 confirmed",
        "source_path": "harness/docs/architecture/README.md",
        "source_section": "Index types \u2014 confirmed",
        "source_type": "doc"
      },
      "relations": {
        "conflicts_with": [],
        "extends": [],
        "resolves": [],
        "supersedes": []
      },
      "scope": {
        "api_surfaces": [],
        "domains": [
          "architecture"
        ],
        "paths": [
          "harness/docs/architecture/README.md"
        ]
      },
      "source_status": null,
      "statement": "`active/by-domain/` \u2014 records grouped by scope domain",
      "subject_key": "arch.index.types.confirme.active.by.domain.records.group",
      "tags": [
        "architecture",
        "doc",
        "observed_fact"
      ],
      "temporal": {
        "documented_at": null,
        "effective_at": null,
        "last_verified_at": null
      }
    }
  ]
}
